{"GlobalPropertiesHash":"i47T5bcF7JzAo7a+hVhT5r91oeLENmOlZFrcKG3fNeY=","FingerprintPatternsHash":"gq3WsqcKBUGTSNle7RKKyXRIwh7M8ccEqOqYvIzoM04=","PropertyOverridesHash":"8ZRc1sGeVrPBx4lD717BgRaQekyh78QKV9SKsdt638U=","InputHashes":["PIpe/jRBZ8D/0iMV4TM2q6yQZV9Ph9z9PE3VUYJDkI4=","8mVZV15uur0qLhFbY8CMJx0PblJUNOZZdf5SyDFKWPo=","kYHTHH6wvLmQlZ9paiar3687qrPwUtXHcdI5AV/fTgc="],"CachedAssets":{"PIpe/jRBZ8D/0iMV4TM2q6yQZV9Ph9z9PE3VUYJDkI4=":{"Identity":"C:\\Users\\91784\\Desktop\\ASP.NET\\LearnRouting\\WebApp\\wwwroot\\text.txt","SourceId":"WebApp","SourceType":"Discovered","ContentRoot":"C:\\Users\\91784\\Desktop\\ASP.NET\\LearnRouting\\WebApp\\wwwroot\\","BasePath":"_content/WebApp","RelativePath":"text#[.{fingerprint}]?.txt","AssetKind":"All","AssetMode":"All","AssetRole":"Primary","AssetMergeBehavior":null,"AssetMergeSource":"","RelatedAsset":null,"AssetTraitName":null,"AssetTraitValue":null,"Fingerprint":"op2scmum26","Integrity":"vAA5XeMA8zRM5rj8D0jcnKhj9jjuIae9W59L9xXTiiw=","CopyToOutputDirectory":"Never","CopyToPublishDirectory":"PreserveNewest","OriginalItemSpec":"wwwroot\\text.txt","FileLength":31,"LastWriteTime":"2026-01-30T10:40:42.7191572+00:00"}},"CachedCopyCandidates":{}}